fable_sedlex/__init__.py
fable_sedlex/bug.py
fable_sedlex/code_gen_julia.py
fable_sedlex/code_gen_python.py
fable_sedlex/fable_modules/__init__.py
fable_sedlex/fable_modules/fable_library/__init__.py
fable_sedlex/fable_modules/fable_library/array.py
fable_sedlex/fable_modules/fable_library/async_.py
fable_sedlex/fable_modules/fable_library/async_builder.py
fable_sedlex/fable_modules/fable_library/big_int.py
fable_sedlex/fable_modules/fable_library/bit_converter.py
fable_sedlex/fable_modules/fable_library/boolean.py
fable_sedlex/fable_modules/fable_library/char.py
fable_sedlex/fable_modules/fable_library/choice.py
fable_sedlex/fable_modules/fable_library/date.py
fable_sedlex/fable_modules/fable_library/date_offset.py
fable_sedlex/fable_modules/fable_library/decimal.py
fable_sedlex/fable_modules/fable_library/double.py
fable_sedlex/fable_modules/fable_library/fable_modules/project_cracked.json
fable_sedlex/fable_modules/fable_library/fsharp_collections.py
fable_sedlex/fable_modules/fable_library/fsharp_core.py
fable_sedlex/fable_modules/fable_library/global_.py
fable_sedlex/fable_modules/fable_library/guid.py
fable_sedlex/fable_modules/fable_library/int32.py
fable_sedlex/fable_modules/fable_library/list.py
fable_sedlex/fable_modules/fable_library/long.py
fable_sedlex/fable_modules/fable_library/mailbox_processor.py
fable_sedlex/fable_modules/fable_library/map.py
fable_sedlex/fable_modules/fable_library/map_util.py
fable_sedlex/fable_modules/fable_library/mutable_map.py
fable_sedlex/fable_modules/fable_library/mutable_set.py
fable_sedlex/fable_modules/fable_library/native.py
fable_sedlex/fable_modules/fable_library/numeric.py
fable_sedlex/fable_modules/fable_library/observable.py
fable_sedlex/fable_modules/fable_library/option.py
fable_sedlex/fable_modules/fable_library/range.py
fable_sedlex/fable_modules/fable_library/reflection.py
fable_sedlex/fable_modules/fable_library/reg_exp.py
fable_sedlex/fable_modules/fable_library/resize_array.py
fable_sedlex-0.2.0.dist-info/LICENSE
fable_sedlex-0.2.0.dist-info/WHEEL
fable_sedlex-0.2.0.dist-info/METADATA
fable_sedlex-0.2.0.dist-info/RECORD
