Metadata-Version: 2.1
Name: fable-sedlex
Version: 0.2.0
Summary: language agnostic lexer generator via Fable and OCaml Sedlex
License: MIT
Author: thautwarm
Author-email: twshere@outlook.com
Requires-Python: >=3.8,<4.0
Classifier: License :: OSI Approved :: MIT License
Classifier: Programming Language :: Python :: 3
Classifier: Programming Language :: Python :: 3.10
Classifier: Programming Language :: Python :: 3.8
Classifier: Programming Language :: Python :: 3.9
